fastdla/__init__.py
fastdla/eigenspace.py
fastdla/lie_closure.py
fastdla/pauli.py
fastdla/projection.py
fastdla/sparse_pauli_sum.py
fastdla/sps_fast.py
fastdla/_lie_closure_impl/matrix_jax.py
fastdla/_lie_closure_impl/pauli_vector.py
fastdla/_lie_closure_impl/sparse_numba.py
fastdla/generators/__init__.py
fastdla/generators/hea.py
fastdla/generators/heisenberg_hva.py
fastdla/generators/spin_chain.py
fastdla/generators/spin_glass.py
fastdla/generators/tfim_hva.py
fastdla/generators/z2lgt_hva.py
fastdla-0.8.3.dist-info/METADATA
fastdla-0.8.3.dist-info/WHEEL
fastdla-0.8.3.dist-info/licenses/LICENSE
fastdla-0.8.3.dist-info/RECORD
